gloomy/__init__.py
gloomy/gloom.py
gloomy-0.2.5.dist-info/METADATA
gloomy-0.2.5.dist-info/WHEEL
gloomy-0.2.5.dist-info/licenses/LICENSE
gloomy-0.2.5.dist-info/RECORD
